sei_py/__init__.py
sei_py/helpers.py
sei_py/sei.py
sei_py/base/__init__.py
sei_py/base/exception.py
sei_py/base/page.py
sei_py/base/providers.py
sei_py/rest/__init__.py
sei_py/rest/delivery.py
sei_py/rest/exam.py
sei_py/rest/integration.py
sei_py/rest/item.py
sei_py-0.2.0.dist-info/DESCRIPTION.rst
sei_py-0.2.0.dist-info/METADATA
sei_py-0.2.0.dist-info/RECORD
sei_py-0.2.0.dist-info/WHEEL
sei_py-0.2.0.dist-info/metadata.json
sei_py-0.2.0.dist-info/top_level.txt
