Metadata-Version: 2.0
Name: sei-py
Version: 0.2.0
Summary: A Caveon SEI helper library
Home-page: https://github.com/xh4zr/sei-py
Author: Evan Anderson
Author-email: evan.anderson@caveon.com
License: UNKNOWN
Keywords: caveon,sei,exam,test security
Platform: UNKNOWN
Requires-Dist: python-jwt (==2.0.2)
Requires-Dist: requests (==2.18.4)
